pyaec/__init__.py
pyaec/aec.dll
pyaec-1.0.1.dist-info/METADATA
pyaec-1.0.1.dist-info/WHEEL
pyaec-1.0.1.dist-info/RECORD
