Metadata-Version: 2.3
Name: pyaec
Version: 1.0.1
Summary: Acoustic echo cancellation
Author-email: thewh1teagle <61390950+thewh1teagle@users.noreply.github.com>
Requires-Python: >=3.6
